lemmy_image_purge/__init__.py
lemmy_image_purge/cli.py
lemmy_image_purge/main.py
lemmy_image_purge/settings.py
lemmy_image_purge-1.0.0.dist-info/LICENSE
lemmy_image_purge-1.0.0.dist-info/METADATA
lemmy_image_purge-1.0.0.dist-info/WHEEL
lemmy_image_purge-1.0.0.dist-info/entry_points.txt
lemmy_image_purge-1.0.0.dist-info/RECORD
