Metadata-Version: 2.1
Name: lemmy-image-purge
Version: 1.0.0
Summary: Purge Images from your Lemmy Instance
License: MIT
Author: Chris Pressland
Author-email: mail@cpressland.io
Requires-Python: >=3.11,<4.0
Classifier: License :: OSI Approved :: MIT License
Classifier: Programming Language :: Python :: 3
Classifier: Programming Language :: Python :: 3.11
Requires-Dist: click (>=8.1.7,<9.0.0)
Requires-Dist: loguru (>=0.7.0,<0.8.0)
Requires-Dist: pendulum (>=2.1.2,<3.0.0)
Requires-Dist: psycopg2-binary (>=2.9.7,<3.0.0)
Requires-Dist: pydantic-settings (>=2.0.3,<3.0.0)
Requires-Dist: requests (>=2.31.0,<3.0.0)
Requires-Dist: sqlalchemy (>=2.0.20,<3.0.0)
